sqlalchemy_pgspider/__init__.py
sqlalchemy_pgspider/psycopg2.py
sqlalchemy_pgspider-0.1.0.dist-info/LICENSE
sqlalchemy_pgspider-0.1.0.dist-info/METADATA
sqlalchemy_pgspider-0.1.0.dist-info/WHEEL
sqlalchemy_pgspider-0.1.0.dist-info/entry_points.txt
sqlalchemy_pgspider-0.1.0.dist-info/RECORD
