Metadata-Version: 2.1
Name: sqlalchemy-pgspider
Version: 0.1.0
Summary: PGSpider Dialect for SQLAlchemy
Home-page: https://github.com/pgspider/sqlalchemy-pgspider
License: MIT
Author: TOSHIBA Corporation
Requires-Python: >=3.7,<4.0
Classifier: License :: OSI Approved :: MIT License
Classifier: Programming Language :: Python :: 3
Classifier: Programming Language :: Python :: 3.7
Classifier: Programming Language :: Python :: 3.8
Classifier: Programming Language :: Python :: 3.9
Classifier: Programming Language :: Python :: 3.10
Classifier: Programming Language :: Python :: 3.11
Project-URL: Repository, https://github.com/pgspider/sqlalchemy-pgspider
